<stg><name>double_subtraction</name>


<trans_list>

<trans id="65" from="1" to="2">
<condition id="-1">
<or_exp><and_exp></and_exp></or_exp>
</condition>
</trans>

<trans id="105" from="2" to="20">
<condition id="-1">
<or_exp><and_exp><literal name="tmp_1" val="0"/>
</and_exp><and_exp><literal name="tmp" val="0"/>
</and_exp></or_exp>
</condition>
</trans>

<trans id="106" from="2" to="3">
<condition id="-1">
<or_exp><and_exp><literal name="tmp" val="1"/>
<literal name="tmp_1" val="1"/>
</and_exp></or_exp>
</condition>
</trans>

<trans id="88" from="3" to="4">
<condition id="-1">
<or_exp><and_exp></and_exp></or_exp>
</condition>
</trans>

<trans id="89" from="4" to="5">
<condition id="-1">
<or_exp><and_exp></and_exp></or_exp>
</condition>
</trans>

<trans id="90" from="5" to="6">
<condition id="-1">
<or_exp><and_exp></and_exp></or_exp>
</condition>
</trans>

<trans id="91" from="6" to="7">
<condition id="-1">
<or_exp><and_exp></and_exp></or_exp>
</condition>
</trans>

<trans id="92" from="7" to="8">
<condition id="-1">
<or_exp><and_exp></and_exp></or_exp>
</condition>
</trans>

<trans id="93" from="8" to="9">
<condition id="-1">
<or_exp><and_exp></and_exp></or_exp>
</condition>
</trans>

<trans id="94" from="9" to="10">
<condition id="-1">
<or_exp><and_exp></and_exp></or_exp>
</condition>
</trans>

<trans id="95" from="10" to="11">
<condition id="-1">
<or_exp><and_exp></and_exp></or_exp>
</condition>
</trans>

<trans id="96" from="11" to="12">
<condition id="-1">
<or_exp><and_exp></and_exp></or_exp>
</condition>
</trans>

<trans id="97" from="12" to="13">
<condition id="-1">
<or_exp><and_exp></and_exp></or_exp>
</condition>
</trans>

<trans id="98" from="13" to="14">
<condition id="-1">
<or_exp><and_exp></and_exp></or_exp>
</condition>
</trans>

<trans id="99" from="14" to="15">
<condition id="-1">
<or_exp><and_exp></and_exp></or_exp>
</condition>
</trans>

<trans id="100" from="15" to="16">
<condition id="-1">
<or_exp><and_exp></and_exp></or_exp>
</condition>
</trans>

<trans id="101" from="16" to="17">
<condition id="-1">
<or_exp><and_exp></and_exp></or_exp>
</condition>
</trans>

<trans id="102" from="17" to="18">
<condition id="-1">
<or_exp><and_exp></and_exp></or_exp>
</condition>
</trans>

<trans id="103" from="18" to="19">
<condition id="-1">
<or_exp><and_exp></and_exp></or_exp>
</condition>
</trans>

<trans id="104" from="19" to="2">
<condition id="-1">
<or_exp><and_exp></and_exp></or_exp>
</condition>
</trans>
</trans_list>



<state_list>

<state id="1" st_id="1">

<operation id="21" st_id="1" stage="1" lat="1">
<core>NULL</core>
<MemPortIdVec></MemPortIdVec>
<condition id="-1">
<or_exp><and_exp></and_exp></or_exp>
</condition>

<Node id="4" bw="32" op_0_bw="32" op_1_bw="16" op_2_bw="0" op_3_bw="32" op_4_bw="32" op_5_bw="0" op_6_bw="32" op_7_bw="32" op_8_bw="0" op_9_bw="0" op_10_bw="0" op_11_bw="32" op_12_bw="32" op_13_bw="32" op_14_bw="32" op_15_bw="0" op_16_bw="0">
<![CDATA[
:0  %empty = call i32 (...)* @_ssdm_op_SpecInterface(half* %c_V, [8 x i8]* @ap_fifo_str, i32 0, i32 0, [1 x i8]* @p_str, i32 0, i32 0, [1 x i8]* @p_str, [1 x i8]* @p_str, [1 x i8]* @p_str, i32 2, i32 2, i32 16, i32 16, [1 x i8]* @p_str, [1 x i8]* @p_str)

]]></Node>
<StgValue><ssdm name="empty"/></StgValue>
</operation>

<operation id="22" st_id="1" stage="1" lat="1">
<core>NULL</core>
<MemPortIdVec></MemPortIdVec>
<condition id="-1">
<or_exp><and_exp></and_exp></or_exp>
</condition>

<Node id="5" bw="32" op_0_bw="32" op_1_bw="16" op_2_bw="0" op_3_bw="32" op_4_bw="32" op_5_bw="0" op_6_bw="32" op_7_bw="32" op_8_bw="0" op_9_bw="0" op_10_bw="0" op_11_bw="32" op_12_bw="32" op_13_bw="32" op_14_bw="32" op_15_bw="0" op_16_bw="0">
<![CDATA[
:1  %empty_3 = call i32 (...)* @_ssdm_op_SpecInterface(i16* %b_V, [8 x i8]* @ap_fifo_str, i32 0, i32 0, [1 x i8]* @p_str, i32 0, i32 0, [1 x i8]* @p_str, [1 x i8]* @p_str, [1 x i8]* @p_str, i32 2, i32 2, i32 16, i32 16, [1 x i8]* @p_str, [1 x i8]* @p_str)

]]></Node>
<StgValue><ssdm name="empty_3"/></StgValue>
</operation>

<operation id="23" st_id="1" stage="1" lat="1">
<core>NULL</core>
<MemPortIdVec></MemPortIdVec>
<condition id="-1">
<or_exp><and_exp></and_exp></or_exp>
</condition>

<Node id="6" bw="32" op_0_bw="32" op_1_bw="16" op_2_bw="0" op_3_bw="32" op_4_bw="32" op_5_bw="0" op_6_bw="32" op_7_bw="32" op_8_bw="0" op_9_bw="0" op_10_bw="0" op_11_bw="32" op_12_bw="32" op_13_bw="32" op_14_bw="32" op_15_bw="0" op_16_bw="0">
<![CDATA[
:2  %empty_4 = call i32 (...)* @_ssdm_op_SpecInterface(i16* %a_V, [8 x i8]* @ap_fifo_str, i32 0, i32 0, [1 x i8]* @p_str, i32 0, i32 0, [1 x i8]* @p_str, [1 x i8]* @p_str, [1 x i8]* @p_str, i32 2, i32 2, i32 16, i32 16, [1 x i8]* @p_str, [1 x i8]* @p_str)

]]></Node>
<StgValue><ssdm name="empty_4"/></StgValue>
</operation>

<operation id="24" st_id="1" stage="1" lat="1">
<core>NULL</core>
<MemPortIdVec></MemPortIdVec>
<condition id="-1">
<or_exp><and_exp></and_exp></or_exp>
</condition>

<Node id="7" bw="0" op_0_bw="0" op_1_bw="16">
<![CDATA[
:3  call void (...)* @_ssdm_op_SpecBitsMap(i16* %a_V), !map !112

]]></Node>
<StgValue><ssdm name="specbitsmap_ln0"/></StgValue>
</operation>

<operation id="25" st_id="1" stage="1" lat="1">
<core>NULL</core>
<MemPortIdVec></MemPortIdVec>
<condition id="-1">
<or_exp><and_exp></and_exp></or_exp>
</condition>

<Node id="8" bw="0" op_0_bw="0" op_1_bw="16">
<![CDATA[
:4  call void (...)* @_ssdm_op_SpecBitsMap(i16* %b_V), !map !116

]]></Node>
<StgValue><ssdm name="specbitsmap_ln0"/></StgValue>
</operation>

<operation id="26" st_id="1" stage="1" lat="1">
<core>NULL</core>
<MemPortIdVec></MemPortIdVec>
<condition id="-1">
<or_exp><and_exp></and_exp></or_exp>
</condition>

<Node id="9" bw="0" op_0_bw="0" op_1_bw="16">
<![CDATA[
:5  call void (...)* @_ssdm_op_SpecBitsMap(half* %c_V), !map !120

]]></Node>
<StgValue><ssdm name="specbitsmap_ln0"/></StgValue>
</operation>

<operation id="27" st_id="1" stage="1" lat="1">
<core>NULL</core>
<MemPortIdVec></MemPortIdVec>
<condition id="-1">
<or_exp><and_exp></and_exp></or_exp>
</condition>

<Node id="10" bw="0" op_0_bw="0" op_1_bw="0">
<![CDATA[
:6  call void (...)* @_ssdm_op_SpecTopModule([19 x i8]* @double_subtraction_s) nounwind

]]></Node>
<StgValue><ssdm name="spectopmodule_ln0"/></StgValue>
</operation>

<operation id="28" st_id="1" stage="1" lat="1">
<core>NULL</core>
<MemPortIdVec></MemPortIdVec>
<condition id="-1">
<or_exp><and_exp></and_exp></or_exp>
</condition>

<Node id="11" bw="0" op_0_bw="0">
<![CDATA[
:7  br label %1

]]></Node>
<StgValue><ssdm name="br_ln21"/></StgValue>
</operation>
</state>

<state id="2" st_id="2">

<operation id="29" st_id="2" stage="1" lat="1">
<core>FIFO</core>
<MemPortIdVec></MemPortIdVec>
<condition id="-1">
<or_exp><and_exp></and_exp></or_exp>
</condition>

<Node id="13" bw="1" op_0_bw="1" op_1_bw="16" op_2_bw="32">
<![CDATA[
:0  %tmp = call i1 @_ssdm_op_NbReadReq.ap_fifo.i16P(i16* %a_V, i32 1)

]]></Node>
<StgValue><ssdm name="tmp"/></StgValue>
</operation>

<operation id="30" st_id="2" stage="1" lat="1">
<core>NULL</core>
<MemPortIdVec></MemPortIdVec>
<condition id="-1">
<or_exp><and_exp></and_exp></or_exp>
</condition>

<Node id="14" bw="0" op_0_bw="1" op_1_bw="0" op_2_bw="0">
<![CDATA[
:1  br i1 %tmp, label %2, label %.critedge

]]></Node>
<StgValue><ssdm name="br_ln21"/></StgValue>
</operation>

<operation id="31" st_id="2" stage="1" lat="1">
<core>FIFO</core>
<MemPortIdVec></MemPortIdVec>
<condition id="-1">
<or_exp><and_exp><literal name="tmp" val="1"/>
</and_exp></or_exp>
</condition>

<Node id="16" bw="1" op_0_bw="1" op_1_bw="16" op_2_bw="32">
<![CDATA[
:0  %tmp_1 = call i1 @_ssdm_op_NbReadReq.ap_fifo.i16P(i16* %b_V, i32 1)

]]></Node>
<StgValue><ssdm name="tmp_1"/></StgValue>
</operation>

<operation id="32" st_id="2" stage="1" lat="1">
<core>NULL</core>
<MemPortIdVec></MemPortIdVec>
<condition id="-1">
<or_exp><and_exp><literal name="tmp" val="1"/>
</and_exp></or_exp>
</condition>

<Node id="17" bw="0" op_0_bw="1" op_1_bw="0" op_2_bw="0">
<![CDATA[
:1  br i1 %tmp_1, label %hls_label_0, label %.critedge

]]></Node>
<StgValue><ssdm name="br_ln21"/></StgValue>
</operation>

<operation id="33" st_id="2" stage="1" lat="1">
<core>FIFO</core>
<MemPortIdVec></MemPortIdVec>
<condition id="-1">
<or_exp><and_exp><literal name="tmp" val="1"/>
<literal name="tmp_1" val="1"/>
</and_exp></or_exp>
</condition>

<Node id="21" bw="16" op_0_bw="16" op_1_bw="16" op_2_bw="1">
<![CDATA[
hls_label_0:2  %tmp_3 = call i16 @_ssdm_op_Read.ap_fifo.volatile.i16P(i16* %a_V)

]]></Node>
<StgValue><ssdm name="tmp_3"/></StgValue>
</operation>

<operation id="34" st_id="2" stage="1" lat="1">
<core>FIFO</core>
<MemPortIdVec></MemPortIdVec>
<condition id="-1">
<or_exp><and_exp><literal name="tmp" val="1"/>
<literal name="tmp_1" val="1"/>
</and_exp></or_exp>
</condition>

<Node id="24" bw="16" op_0_bw="16" op_1_bw="16" op_2_bw="1">
<![CDATA[
hls_label_0:5  %tmp_4 = call i16 @_ssdm_op_Read.ap_fifo.volatile.i16P(i16* %b_V)

]]></Node>
<StgValue><ssdm name="tmp_4"/></StgValue>
</operation>
</state>

<state id="3" st_id="3">

<operation id="35" st_id="3" stage="1" lat="1">
<core>NULL</core>
<MemPortIdVec></MemPortIdVec>
<condition id="-1">
<or_exp><and_exp><literal name="tmp_1" val="1"/>
</and_exp></or_exp>
</condition>

<Node id="22" bw="32" op_0_bw="16">
<![CDATA[
hls_label_0:3  %sext_ln28 = sext i16 %tmp_3 to i32

]]></Node>
<StgValue><ssdm name="sext_ln28"/></StgValue>
</operation>

<operation id="36" st_id="3" stage="5" lat="5">
<core>Int2Double</core>
<MemPortIdVec></MemPortIdVec>
<condition id="-1">
<or_exp><and_exp><literal name="tmp_1" val="1"/>
</and_exp></or_exp>
</condition>

<Node id="23" bw="64" op_0_bw="32">
<![CDATA[
hls_label_0:4  %d = sitofp i32 %sext_ln28 to double

]]></Node>
<StgValue><ssdm name="d"/></StgValue>
</operation>

<operation id="37" st_id="3" stage="1" lat="1">
<core>NULL</core>
<MemPortIdVec></MemPortIdVec>
<condition id="-1">
<or_exp><and_exp><literal name="tmp_1" val="1"/>
</and_exp></or_exp>
</condition>

<Node id="25" bw="32" op_0_bw="16">
<![CDATA[
hls_label_0:6  %sext_ln29 = sext i16 %tmp_4 to i32

]]></Node>
<StgValue><ssdm name="sext_ln29"/></StgValue>
</operation>

<operation id="38" st_id="3" stage="5" lat="5">
<core>Int2Double</core>
<MemPortIdVec></MemPortIdVec>
<condition id="-1">
<or_exp><and_exp><literal name="tmp_1" val="1"/>
</and_exp></or_exp>
</condition>

<Node id="26" bw="64" op_0_bw="32">
<![CDATA[
hls_label_0:7  %e = sitofp i32 %sext_ln29 to double

]]></Node>
<StgValue><ssdm name="e"/></StgValue>
</operation>
</state>

<state id="4" st_id="4">

<operation id="39" st_id="4" stage="4" lat="5">
<core>Int2Double</core>
<MemPortIdVec></MemPortIdVec>
<condition id="-1">
<or_exp><and_exp><literal name="tmp_1" val="1"/>
</and_exp></or_exp>
</condition>

<Node id="23" bw="64" op_0_bw="32">
<![CDATA[
hls_label_0:4  %d = sitofp i32 %sext_ln28 to double

]]></Node>
<StgValue><ssdm name="d"/></StgValue>
</operation>

<operation id="40" st_id="4" stage="4" lat="5">
<core>Int2Double</core>
<MemPortIdVec></MemPortIdVec>
<condition id="-1">
<or_exp><and_exp><literal name="tmp_1" val="1"/>
</and_exp></or_exp>
</condition>

<Node id="26" bw="64" op_0_bw="32">
<![CDATA[
hls_label_0:7  %e = sitofp i32 %sext_ln29 to double

]]></Node>
<StgValue><ssdm name="e"/></StgValue>
</operation>
</state>

<state id="5" st_id="5">

<operation id="41" st_id="5" stage="3" lat="5">
<core>Int2Double</core>
<MemPortIdVec></MemPortIdVec>
<condition id="-1">
<or_exp><and_exp><literal name="tmp_1" val="1"/>
</and_exp></or_exp>
</condition>

<Node id="23" bw="64" op_0_bw="32">
<![CDATA[
hls_label_0:4  %d = sitofp i32 %sext_ln28 to double

]]></Node>
<StgValue><ssdm name="d"/></StgValue>
</operation>

<operation id="42" st_id="5" stage="3" lat="5">
<core>Int2Double</core>
<MemPortIdVec></MemPortIdVec>
<condition id="-1">
<or_exp><and_exp><literal name="tmp_1" val="1"/>
</and_exp></or_exp>
</condition>

<Node id="26" bw="64" op_0_bw="32">
<![CDATA[
hls_label_0:7  %e = sitofp i32 %sext_ln29 to double

]]></Node>
<StgValue><ssdm name="e"/></StgValue>
</operation>
</state>

<state id="6" st_id="6">

<operation id="43" st_id="6" stage="2" lat="5">
<core>Int2Double</core>
<MemPortIdVec></MemPortIdVec>
<condition id="-1">
<or_exp><and_exp><literal name="tmp_1" val="1"/>
</and_exp></or_exp>
</condition>

<Node id="23" bw="64" op_0_bw="32">
<![CDATA[
hls_label_0:4  %d = sitofp i32 %sext_ln28 to double

]]></Node>
<StgValue><ssdm name="d"/></StgValue>
</operation>

<operation id="44" st_id="6" stage="2" lat="5">
<core>Int2Double</core>
<MemPortIdVec></MemPortIdVec>
<condition id="-1">
<or_exp><and_exp><literal name="tmp_1" val="1"/>
</and_exp></or_exp>
</condition>

<Node id="26" bw="64" op_0_bw="32">
<![CDATA[
hls_label_0:7  %e = sitofp i32 %sext_ln29 to double

]]></Node>
<StgValue><ssdm name="e"/></StgValue>
</operation>
</state>

<state id="7" st_id="7">

<operation id="45" st_id="7" stage="1" lat="5">
<core>Int2Double</core>
<MemPortIdVec></MemPortIdVec>
<condition id="-1">
<or_exp><and_exp><literal name="tmp_1" val="1"/>
</and_exp></or_exp>
</condition>

<Node id="23" bw="64" op_0_bw="32">
<![CDATA[
hls_label_0:4  %d = sitofp i32 %sext_ln28 to double

]]></Node>
<StgValue><ssdm name="d"/></StgValue>
</operation>

<operation id="46" st_id="7" stage="1" lat="5">
<core>Int2Double</core>
<MemPortIdVec></MemPortIdVec>
<condition id="-1">
<or_exp><and_exp><literal name="tmp_1" val="1"/>
</and_exp></or_exp>
</condition>

<Node id="26" bw="64" op_0_bw="32">
<![CDATA[
hls_label_0:7  %e = sitofp i32 %sext_ln29 to double

]]></Node>
<StgValue><ssdm name="e"/></StgValue>
</operation>
</state>

<state id="8" st_id="8">

<operation id="47" st_id="8" stage="5" lat="5">
<core>DAddSub</core>
<MemPortIdVec></MemPortIdVec>
<condition id="-1">
<or_exp><and_exp><literal name="tmp_1" val="1"/>
</and_exp></or_exp>
</condition>

<Node id="27" bw="64" op_0_bw="64" op_1_bw="64">
<![CDATA[
hls_label_0:8  %tmp_5 = fsub double %d, %e

]]></Node>
<StgValue><ssdm name="tmp_5"/></StgValue>
</operation>
</state>

<state id="9" st_id="9">

<operation id="48" st_id="9" stage="4" lat="5">
<core>DAddSub</core>
<MemPortIdVec></MemPortIdVec>
<condition id="-1">
<or_exp><and_exp><literal name="tmp_1" val="1"/>
</and_exp></or_exp>
</condition>

<Node id="27" bw="64" op_0_bw="64" op_1_bw="64">
<![CDATA[
hls_label_0:8  %tmp_5 = fsub double %d, %e

]]></Node>
<StgValue><ssdm name="tmp_5"/></StgValue>
</operation>
</state>

<state id="10" st_id="10">

<operation id="49" st_id="10" stage="3" lat="5">
<core>DAddSub</core>
<MemPortIdVec></MemPortIdVec>
<condition id="-1">
<or_exp><and_exp><literal name="tmp_1" val="1"/>
</and_exp></or_exp>
</condition>

<Node id="27" bw="64" op_0_bw="64" op_1_bw="64">
<![CDATA[
hls_label_0:8  %tmp_5 = fsub double %d, %e

]]></Node>
<StgValue><ssdm name="tmp_5"/></StgValue>
</operation>
</state>

<state id="11" st_id="11">

<operation id="50" st_id="11" stage="2" lat="5">
<core>DAddSub</core>
<MemPortIdVec></MemPortIdVec>
<condition id="-1">
<or_exp><and_exp><literal name="tmp_1" val="1"/>
</and_exp></or_exp>
</condition>

<Node id="27" bw="64" op_0_bw="64" op_1_bw="64">
<![CDATA[
hls_label_0:8  %tmp_5 = fsub double %d, %e

]]></Node>
<StgValue><ssdm name="tmp_5"/></StgValue>
</operation>
</state>

<state id="12" st_id="12">

<operation id="51" st_id="12" stage="1" lat="5">
<core>DAddSub</core>
<MemPortIdVec></MemPortIdVec>
<condition id="-1">
<or_exp><and_exp><literal name="tmp_1" val="1"/>
</and_exp></or_exp>
</condition>

<Node id="27" bw="64" op_0_bw="64" op_1_bw="64">
<![CDATA[
hls_label_0:8  %tmp_5 = fsub double %d, %e

]]></Node>
<StgValue><ssdm name="tmp_5"/></StgValue>
</operation>
</state>

<state id="13" st_id="13">

<operation id="52" st_id="13" stage="5" lat="5">
<core>DMul</core>
<MemPortIdVec></MemPortIdVec>
<condition id="-1">
<or_exp><and_exp><literal name="tmp_1" val="1"/>
</and_exp></or_exp>
</condition>

<Node id="28" bw="64" op_0_bw="64" op_1_bw="64">
<![CDATA[
hls_label_0:9  %f = fmul double %tmp_5, 0x3F234413509F79FF

]]></Node>
<StgValue><ssdm name="f"/></StgValue>
</operation>
</state>

<state id="14" st_id="14">

<operation id="53" st_id="14" stage="4" lat="5">
<core>DMul</core>
<MemPortIdVec></MemPortIdVec>
<condition id="-1">
<or_exp><and_exp><literal name="tmp_1" val="1"/>
</and_exp></or_exp>
</condition>

<Node id="28" bw="64" op_0_bw="64" op_1_bw="64">
<![CDATA[
hls_label_0:9  %f = fmul double %tmp_5, 0x3F234413509F79FF

]]></Node>
<StgValue><ssdm name="f"/></StgValue>
</operation>
</state>

<state id="15" st_id="15">

<operation id="54" st_id="15" stage="3" lat="5">
<core>DMul</core>
<MemPortIdVec></MemPortIdVec>
<condition id="-1">
<or_exp><and_exp><literal name="tmp_1" val="1"/>
</and_exp></or_exp>
</condition>

<Node id="28" bw="64" op_0_bw="64" op_1_bw="64">
<![CDATA[
hls_label_0:9  %f = fmul double %tmp_5, 0x3F234413509F79FF

]]></Node>
<StgValue><ssdm name="f"/></StgValue>
</operation>
</state>

<state id="16" st_id="16">

<operation id="55" st_id="16" stage="2" lat="5">
<core>DMul</core>
<MemPortIdVec></MemPortIdVec>
<condition id="-1">
<or_exp><and_exp><literal name="tmp_1" val="1"/>
</and_exp></or_exp>
</condition>

<Node id="28" bw="64" op_0_bw="64" op_1_bw="64">
<![CDATA[
hls_label_0:9  %f = fmul double %tmp_5, 0x3F234413509F79FF

]]></Node>
<StgValue><ssdm name="f"/></StgValue>
</operation>
</state>

<state id="17" st_id="17">

<operation id="56" st_id="17" stage="1" lat="5">
<core>DMul</core>
<MemPortIdVec></MemPortIdVec>
<condition id="-1">
<or_exp><and_exp><literal name="tmp_1" val="1"/>
</and_exp></or_exp>
</condition>

<Node id="28" bw="64" op_0_bw="64" op_1_bw="64">
<![CDATA[
hls_label_0:9  %f = fmul double %tmp_5, 0x3F234413509F79FF

]]></Node>
<StgValue><ssdm name="f"/></StgValue>
</operation>
</state>

<state id="18" st_id="18">

<operation id="57" st_id="18" stage="2" lat="2">
<core>Double2Half</core>
<MemPortIdVec></MemPortIdVec>
<condition id="-1">
<or_exp><and_exp><literal name="tmp_1" val="1"/>
</and_exp></or_exp>
</condition>

<Node id="29" bw="16" op_0_bw="64">
<![CDATA[
hls_label_0:10  %tmp_6 = fptrunc double %f to half

]]></Node>
<StgValue><ssdm name="tmp_6"/></StgValue>
</operation>
</state>

<state id="19" st_id="19">

<operation id="58" st_id="19" stage="1" lat="1">
<core>NULL</core>
<MemPortIdVec></MemPortIdVec>
<condition id="-1">
<or_exp><and_exp><literal name="tmp_1" val="1"/>
</and_exp></or_exp>
</condition>

<Node id="19" bw="32" op_0_bw="32" op_1_bw="0">
<![CDATA[
hls_label_0:0  %tmp_2 = call i32 (...)* @_ssdm_op_SpecRegionBegin([12 x i8]* @p_str1)

]]></Node>
<StgValue><ssdm name="tmp_2"/></StgValue>
</operation>

<operation id="59" st_id="19" stage="1" lat="1">
<core>NULL</core>
<MemPortIdVec></MemPortIdVec>
<condition id="-1">
<or_exp><and_exp><literal name="tmp_1" val="1"/>
</and_exp></or_exp>
</condition>

<Node id="20" bw="0" op_0_bw="0" op_1_bw="32" op_2_bw="32" op_3_bw="32" op_4_bw="32" op_5_bw="0">
<![CDATA[
hls_label_0:1  call void (...)* @_ssdm_op_SpecPipeline(i32 -1, i32 1, i32 1, i32 0, [1 x i8]* @p_str) nounwind

]]></Node>
<StgValue><ssdm name="specpipeline_ln23"/></StgValue>
</operation>

<operation id="60" st_id="19" stage="1" lat="2">
<core>Double2Half</core>
<MemPortIdVec></MemPortIdVec>
<condition id="-1">
<or_exp><and_exp><literal name="tmp_1" val="1"/>
</and_exp></or_exp>
</condition>

<Node id="29" bw="16" op_0_bw="64">
<![CDATA[
hls_label_0:10  %tmp_6 = fptrunc double %f to half

]]></Node>
<StgValue><ssdm name="tmp_6"/></StgValue>
</operation>

<operation id="61" st_id="19" stage="1" lat="1">
<core>FIFO</core>
<MemPortIdVec></MemPortIdVec>
<condition id="-1">
<or_exp><and_exp><literal name="tmp_1" val="1"/>
</and_exp></or_exp>
</condition>

<Node id="30" bw="0" op_0_bw="0" op_1_bw="16" op_2_bw="16">
<![CDATA[
hls_label_0:11  call void @_ssdm_op_Write.ap_fifo.volatile.halfP(half* %c_V, half %tmp_6)

]]></Node>
<StgValue><ssdm name="write_ln32"/></StgValue>
</operation>

<operation id="62" st_id="19" stage="1" lat="1">
<core>NULL</core>
<MemPortIdVec></MemPortIdVec>
<condition id="-1">
<or_exp><and_exp><literal name="tmp_1" val="1"/>
</and_exp></or_exp>
</condition>

<Node id="31" bw="32" op_0_bw="32" op_1_bw="0" op_2_bw="32">
<![CDATA[
hls_label_0:12  %empty_5 = call i32 (...)* @_ssdm_op_SpecRegionEnd([12 x i8]* @p_str1, i32 %tmp_2)

]]></Node>
<StgValue><ssdm name="empty_5"/></StgValue>
</operation>

<operation id="63" st_id="19" stage="1" lat="1">
<core>NULL</core>
<MemPortIdVec></MemPortIdVec>
<condition id="-1">
<or_exp><and_exp><literal name="tmp_1" val="1"/>
</and_exp></or_exp>
</condition>

<Node id="32" bw="0" op_0_bw="0">
<![CDATA[
hls_label_0:13  br label %1

]]></Node>
<StgValue><ssdm name="br_ln33"/></StgValue>
</operation>
</state>

<state id="20" st_id="20">

<operation id="64" st_id="20" stage="1" lat="1">
<core>NULL</core>
<MemPortIdVec></MemPortIdVec>
<condition id="-1">
<or_exp><and_exp></and_exp></or_exp>
</condition>

<Node id="34" bw="0">
<![CDATA[
.critedge:0  ret void

]]></Node>
<StgValue><ssdm name="ret_ln34"/></StgValue>
</operation>
</state>
</state_list>


<ports>
<port id="107" name="a_V" dir="0" iftype="3">
<core>FIFO</core><StgValue><ssdm name="a_V"/></StgValue>
</port>
<port id="108" name="b_V" dir="0" iftype="3">
<core>FIFO</core><StgValue><ssdm name="b_V"/></StgValue>
</port>
<port id="109" name="c_V" dir="1" iftype="3">
<core>FIFO</core><StgValue><ssdm name="c_V"/></StgValue>
</port>
</ports>


<dataflows>
<dataflow id="111" from="_ssdm_op_SpecInterface" to="empty" fromId="110" toId="21">
</dataflow>
<dataflow id="112" from="c_V" to="empty" fromId="109" toId="21">
</dataflow>
<dataflow id="114" from="ap_fifo_str" to="empty" fromId="113" toId="21">
</dataflow>
<dataflow id="116" from="StgValue_115" to="empty" fromId="115" toId="21">
</dataflow>
<dataflow id="117" from="StgValue_115" to="empty" fromId="115" toId="21">
</dataflow>
<dataflow id="119" from="p_str" to="empty" fromId="118" toId="21">
</dataflow>
<dataflow id="120" from="StgValue_115" to="empty" fromId="115" toId="21">
</dataflow>
<dataflow id="121" from="StgValue_115" to="empty" fromId="115" toId="21">
</dataflow>
<dataflow id="122" from="p_str" to="empty" fromId="118" toId="21">
</dataflow>
<dataflow id="123" from="p_str" to="empty" fromId="118" toId="21">
</dataflow>
<dataflow id="124" from="p_str" to="empty" fromId="118" toId="21">
</dataflow>
<dataflow id="126" from="StgValue_125" to="empty" fromId="125" toId="21">
</dataflow>
<dataflow id="127" from="StgValue_125" to="empty" fromId="125" toId="21">
</dataflow>
<dataflow id="129" from="StgValue_128" to="empty" fromId="128" toId="21">
</dataflow>
<dataflow id="130" from="StgValue_128" to="empty" fromId="128" toId="21">
</dataflow>
<dataflow id="131" from="p_str" to="empty" fromId="118" toId="21">
</dataflow>
<dataflow id="132" from="p_str" to="empty" fromId="118" toId="21">
</dataflow>
<dataflow id="133" from="_ssdm_op_SpecInterface" to="empty_3" fromId="110" toId="22">
</dataflow>
<dataflow id="134" from="b_V" to="empty_3" fromId="108" toId="22">
</dataflow>
<dataflow id="135" from="ap_fifo_str" to="empty_3" fromId="113" toId="22">
</dataflow>
<dataflow id="136" from="StgValue_115" to="empty_3" fromId="115" toId="22">
</dataflow>
<dataflow id="137" from="StgValue_115" to="empty_3" fromId="115" toId="22">
</dataflow>
<dataflow id="138" from="p_str" to="empty_3" fromId="118" toId="22">
</dataflow>
<dataflow id="139" from="StgValue_115" to="empty_3" fromId="115" toId="22">
</dataflow>
<dataflow id="140" from="StgValue_115" to="empty_3" fromId="115" toId="22">
</dataflow>
<dataflow id="141" from="p_str" to="empty_3" fromId="118" toId="22">
</dataflow>
<dataflow id="142" from="p_str" to="empty_3" fromId="118" toId="22">
</dataflow>
<dataflow id="143" from="p_str" to="empty_3" fromId="118" toId="22">
</dataflow>
<dataflow id="144" from="StgValue_125" to="empty_3" fromId="125" toId="22">
</dataflow>
<dataflow id="145" from="StgValue_125" to="empty_3" fromId="125" toId="22">
</dataflow>
<dataflow id="146" from="StgValue_128" to="empty_3" fromId="128" toId="22">
</dataflow>
<dataflow id="147" from="StgValue_128" to="empty_3" fromId="128" toId="22">
</dataflow>
<dataflow id="148" from="p_str" to="empty_3" fromId="118" toId="22">
</dataflow>
<dataflow id="149" from="p_str" to="empty_3" fromId="118" toId="22">
</dataflow>
<dataflow id="150" from="_ssdm_op_SpecInterface" to="empty_4" fromId="110" toId="23">
</dataflow>
<dataflow id="151" from="a_V" to="empty_4" fromId="107" toId="23">
</dataflow>
<dataflow id="152" from="ap_fifo_str" to="empty_4" fromId="113" toId="23">
</dataflow>
<dataflow id="153" from="StgValue_115" to="empty_4" fromId="115" toId="23">
</dataflow>
<dataflow id="154" from="StgValue_115" to="empty_4" fromId="115" toId="23">
</dataflow>
<dataflow id="155" from="p_str" to="empty_4" fromId="118" toId="23">
</dataflow>
<dataflow id="156" from="StgValue_115" to="empty_4" fromId="115" toId="23">
</dataflow>
<dataflow id="157" from="StgValue_115" to="empty_4" fromId="115" toId="23">
</dataflow>
<dataflow id="158" from="p_str" to="empty_4" fromId="118" toId="23">
</dataflow>
<dataflow id="159" from="p_str" to="empty_4" fromId="118" toId="23">
</dataflow>
<dataflow id="160" from="p_str" to="empty_4" fromId="118" toId="23">
</dataflow>
<dataflow id="161" from="StgValue_125" to="empty_4" fromId="125" toId="23">
</dataflow>
<dataflow id="162" from="StgValue_125" to="empty_4" fromId="125" toId="23">
</dataflow>
<dataflow id="163" from="StgValue_128" to="empty_4" fromId="128" toId="23">
</dataflow>
<dataflow id="164" from="StgValue_128" to="empty_4" fromId="128" toId="23">
</dataflow>
<dataflow id="165" from="p_str" to="empty_4" fromId="118" toId="23">
</dataflow>
<dataflow id="166" from="p_str" to="empty_4" fromId="118" toId="23">
</dataflow>
<dataflow id="168" from="_ssdm_op_SpecBitsMap" to="specbitsmap_ln0" fromId="167" toId="24">
</dataflow>
<dataflow id="169" from="a_V" to="specbitsmap_ln0" fromId="107" toId="24">
</dataflow>
<dataflow id="170" from="_ssdm_op_SpecBitsMap" to="specbitsmap_ln0" fromId="167" toId="25">
</dataflow>
<dataflow id="171" from="b_V" to="specbitsmap_ln0" fromId="108" toId="25">
</dataflow>
<dataflow id="172" from="_ssdm_op_SpecBitsMap" to="specbitsmap_ln0" fromId="167" toId="26">
</dataflow>
<dataflow id="173" from="c_V" to="specbitsmap_ln0" fromId="109" toId="26">
</dataflow>
<dataflow id="175" from="_ssdm_op_SpecTopModule" to="spectopmodule_ln0" fromId="174" toId="27">
</dataflow>
<dataflow id="177" from="double_subtraction_s" to="spectopmodule_ln0" fromId="176" toId="27">
</dataflow>
<dataflow id="179" from="_ssdm_op_NbReadReq.ap_fifo.i16P" to="tmp" fromId="178" toId="29">
</dataflow>
<dataflow id="180" from="a_V" to="tmp" fromId="107" toId="29">
</dataflow>
<dataflow id="182" from="StgValue_181" to="tmp" fromId="181" toId="29">
</dataflow>
<dataflow id="183" from="tmp" to="br_ln21" fromId="29" toId="30">
</dataflow>
<dataflow id="184" from="_ssdm_op_NbReadReq.ap_fifo.i16P" to="tmp_1" fromId="178" toId="31">
</dataflow>
<dataflow id="185" from="b_V" to="tmp_1" fromId="108" toId="31">
</dataflow>
<dataflow id="186" from="StgValue_181" to="tmp_1" fromId="181" toId="31">
</dataflow>
<dataflow id="187" from="tmp_1" to="br_ln21" fromId="31" toId="32">
</dataflow>
<dataflow id="189" from="_ssdm_op_Read.ap_fifo.volatile.i16P" to="tmp_3" fromId="188" toId="33">
</dataflow>
<dataflow id="190" from="a_V" to="tmp_3" fromId="107" toId="33">
</dataflow>
<dataflow id="191" from="_ssdm_op_Read.ap_fifo.volatile.i16P" to="tmp_4" fromId="188" toId="34">
</dataflow>
<dataflow id="192" from="b_V" to="tmp_4" fromId="108" toId="34">
</dataflow>
<dataflow id="193" from="tmp_3" to="sext_ln28" fromId="33" toId="35">
</dataflow>
<dataflow id="194" from="sext_ln28" to="d" fromId="35" toId="36">
</dataflow>
<dataflow id="195" from="tmp_4" to="sext_ln29" fromId="34" toId="37">
</dataflow>
<dataflow id="196" from="sext_ln29" to="e" fromId="37" toId="38">
</dataflow>
<dataflow id="197" from="sext_ln28" to="d" fromId="35" toId="39">
</dataflow>
<dataflow id="198" from="sext_ln29" to="e" fromId="37" toId="40">
</dataflow>
<dataflow id="199" from="sext_ln28" to="d" fromId="35" toId="41">
</dataflow>
<dataflow id="200" from="sext_ln29" to="e" fromId="37" toId="42">
</dataflow>
<dataflow id="201" from="sext_ln28" to="d" fromId="35" toId="43">
</dataflow>
<dataflow id="202" from="sext_ln29" to="e" fromId="37" toId="44">
</dataflow>
<dataflow id="203" from="sext_ln28" to="d" fromId="35" toId="45">
</dataflow>
<dataflow id="204" from="sext_ln29" to="e" fromId="37" toId="46">
</dataflow>
<dataflow id="205" from="d" to="tmp_5" fromId="45" toId="47">
</dataflow>
<dataflow id="206" from="e" to="tmp_5" fromId="46" toId="47">
</dataflow>
<dataflow id="207" from="d" to="tmp_5" fromId="45" toId="48">
</dataflow>
<dataflow id="208" from="e" to="tmp_5" fromId="46" toId="48">
</dataflow>
<dataflow id="209" from="d" to="tmp_5" fromId="45" toId="49">
</dataflow>
<dataflow id="210" from="e" to="tmp_5" fromId="46" toId="49">
</dataflow>
<dataflow id="211" from="d" to="tmp_5" fromId="45" toId="50">
</dataflow>
<dataflow id="212" from="e" to="tmp_5" fromId="46" toId="50">
</dataflow>
<dataflow id="213" from="d" to="tmp_5" fromId="45" toId="51">
</dataflow>
<dataflow id="214" from="e" to="tmp_5" fromId="46" toId="51">
</dataflow>
<dataflow id="215" from="tmp_5" to="f" fromId="51" toId="52">
</dataflow>
<dataflow id="217" from="StgValue_216" to="f" fromId="216" toId="52">
</dataflow>
<dataflow id="218" from="tmp_5" to="f" fromId="51" toId="53">
</dataflow>
<dataflow id="219" from="StgValue_216" to="f" fromId="216" toId="53">
</dataflow>
<dataflow id="220" from="tmp_5" to="f" fromId="51" toId="54">
</dataflow>
<dataflow id="221" from="StgValue_216" to="f" fromId="216" toId="54">
</dataflow>
<dataflow id="222" from="tmp_5" to="f" fromId="51" toId="55">
</dataflow>
<dataflow id="223" from="StgValue_216" to="f" fromId="216" toId="55">
</dataflow>
<dataflow id="224" from="tmp_5" to="f" fromId="51" toId="56">
</dataflow>
<dataflow id="225" from="StgValue_216" to="f" fromId="216" toId="56">
</dataflow>
<dataflow id="226" from="f" to="tmp_6" fromId="56" toId="57">
</dataflow>
<dataflow id="228" from="_ssdm_op_SpecRegionBegin" to="tmp_2" fromId="227" toId="58">
</dataflow>
<dataflow id="230" from="p_str1" to="tmp_2" fromId="229" toId="58">
</dataflow>
<dataflow id="232" from="_ssdm_op_SpecPipeline" to="specpipeline_ln23" fromId="231" toId="59">
</dataflow>
<dataflow id="234" from="StgValue_233" to="specpipeline_ln23" fromId="233" toId="59">
</dataflow>
<dataflow id="235" from="StgValue_181" to="specpipeline_ln23" fromId="181" toId="59">
</dataflow>
<dataflow id="236" from="StgValue_181" to="specpipeline_ln23" fromId="181" toId="59">
</dataflow>
<dataflow id="237" from="StgValue_115" to="specpipeline_ln23" fromId="115" toId="59">
</dataflow>
<dataflow id="238" from="p_str" to="specpipeline_ln23" fromId="118" toId="59">
</dataflow>
<dataflow id="239" from="f" to="tmp_6" fromId="56" toId="60">
</dataflow>
<dataflow id="241" from="_ssdm_op_Write.ap_fifo.volatile.halfP" to="write_ln32" fromId="240" toId="61">
</dataflow>
<dataflow id="242" from="c_V" to="write_ln32" fromId="109" toId="61">
</dataflow>
<dataflow id="243" from="tmp_6" to="write_ln32" fromId="60" toId="61">
</dataflow>
<dataflow id="245" from="_ssdm_op_SpecRegionEnd" to="empty_5" fromId="244" toId="62">
</dataflow>
<dataflow id="246" from="p_str1" to="empty_5" fromId="229" toId="62">
</dataflow>
<dataflow id="247" from="tmp_2" to="empty_5" fromId="58" toId="62">
</dataflow>
<dataflow id="248" from="tmp" to="StgValue_2" fromId="29" toId="2">
</dataflow>
<dataflow id="249" from="tmp_1" to="StgValue_2" fromId="31" toId="2">
</dataflow>
<dataflow id="250" from="tmp_1" to="StgValue_3" fromId="31" toId="3">
</dataflow>
<dataflow id="251" from="tmp_1" to="StgValue_4" fromId="31" toId="4">
</dataflow>
<dataflow id="252" from="tmp_1" to="StgValue_5" fromId="31" toId="5">
</dataflow>
<dataflow id="253" from="tmp_1" to="StgValue_6" fromId="31" toId="6">
</dataflow>
<dataflow id="254" from="tmp_1" to="StgValue_7" fromId="31" toId="7">
</dataflow>
<dataflow id="255" from="tmp_1" to="StgValue_8" fromId="31" toId="8">
</dataflow>
<dataflow id="256" from="tmp_1" to="StgValue_9" fromId="31" toId="9">
</dataflow>
<dataflow id="257" from="tmp_1" to="StgValue_10" fromId="31" toId="10">
</dataflow>
<dataflow id="258" from="tmp_1" to="StgValue_11" fromId="31" toId="11">
</dataflow>
<dataflow id="259" from="tmp_1" to="StgValue_12" fromId="31" toId="12">
</dataflow>
<dataflow id="260" from="tmp_1" to="StgValue_13" fromId="31" toId="13">
</dataflow>
<dataflow id="261" from="tmp_1" to="StgValue_14" fromId="31" toId="14">
</dataflow>
<dataflow id="262" from="tmp_1" to="StgValue_15" fromId="31" toId="15">
</dataflow>
<dataflow id="263" from="tmp_1" to="StgValue_16" fromId="31" toId="16">
</dataflow>
<dataflow id="264" from="tmp_1" to="StgValue_17" fromId="31" toId="17">
</dataflow>
<dataflow id="265" from="tmp_1" to="StgValue_18" fromId="31" toId="18">
</dataflow>
<dataflow id="266" from="tmp_1" to="StgValue_19" fromId="31" toId="19">
</dataflow>
</dataflows>


</stg>
